{"data":[{"id":"1","name":"Players","icone":"https://www.dev.ayamesoft.com/lib/upload/parcinfo/family_1.jpg","total":"927","lien":"https://www.dev.ayamesoft.com/plugnweb/word_app?call_func=change_family&id_family=1"},{"id":"2","name":"Tablette PC","icone":"https://www.dev.ayamesoft.com/lib/upload/parcinfo/family_2.jpg","total":"0","lien":"https://www.dev.ayamesoft.com/plugnweb/word_app?call_func=change_family&id_family=2"},{"id":"3","name":"Lecteur multi-média","icone":"https://www.dev.ayamesoft.com/lib/upload/parcinfo/family_3.jpg","total":"0","lien":"https://www.dev.ayamesoft.com/plugnweb/word_app?call_func=change_family&id_family=3"},{"id":"4","name":"Pièces détachées","icone":"https://www.dev.ayamesoft.com/lib/upload/parcinfo/family_4.jpg","total":"0","lien":"https://www.dev.ayamesoft.com/plugnweb/word_app?call_func=change_family&id_family=4"},{"id":"5","name":"Ecran LED","icone":"https://www.dev.ayamesoft.com/lib/upload/parcinfo/family_5.jpg","total":"59","lien":"https://www.dev.ayamesoft.com/plugnweb/word_app?call_func=change_family&id_family=5"},{"id":"6","name":"Téléviseur LCD","icone":"https://www.dev.ayamesoft.com/lib/upload/parcinfo/family_6.jpg","total":"82","lien":"https://www.dev.ayamesoft.com/plugnweb/word_app?call_func=change_family&id_family=6"},{"id":"7","name":"Moniteur LCD","icone":"https://www.dev.ayamesoft.com/lib/upload/parcinfo/family_7.jpg","total":"35","lien":"https://www.dev.ayamesoft.com/plugnweb/word_app?call_func=change_family&id_family=7"},{"id":"8","name":"POS","icone":"https://www.dev.ayamesoft.com/lib/upload/parcinfo/family_8.jpg","total":"0","lien":"https://www.dev.ayamesoft.com/plugnweb/word_app?call_func=change_family&id_family=8"},{"id":"9","name":"Ordinateur portable","icone":"https://www.dev.ayamesoft.com/lib/upload/parcinfo/family_9.jpg","total":"0","lien":"https://www.dev.ayamesoft.com/plugnweb/word_app?call_func=change_family&id_family=9"},{"id":"10","name":"Ecran STRETCH","icone":"https://www.dev.ayamesoft.com/lib/upload/parcinfo/family_10.jpg","total":"0","lien":"https://www.dev.ayamesoft.com/plugnweb/word_app?call_func=change_family&id_family=10"},{"id":"11","name":"Tablette Android","icone":"https://www.dev.ayamesoft.com/lib/upload/parcinfo/family_11.jpg","total":"0","lien":"https://www.dev.ayamesoft.com/plugnweb/word_app?call_func=change_family&id_family=11"},{"id":"12","name":"Hologramme","icone":"https://www.dev.ayamesoft.com/lib/upload/parcinfo/family_12.jpg","total":"38","lien":"https://www.dev.ayamesoft.com/plugnweb/word_app?call_func=change_family&id_family=12"},{"id":"13","name":"Ecran stretch réglette","icone":"https://www.dev.ayamesoft.com/lib/upload/parcinfo/family_13.jpg","total":"1","lien":"https://www.dev.ayamesoft.com/plugnweb/word_app?call_func=change_family&id_family=13"},{"id":"14","name":"Imprimantes","icone":"https://www.dev.ayamesoft.com/lib/upload/parcinfo/family_14.jpg","total":"0","lien":"https://www.dev.ayamesoft.com/plugnweb/word_app?call_func=change_family&id_family=14"},{"id":"15","name":"Accessoires vidéo & réseau","icone":"https://www.dev.ayamesoft.com/lib/upload/parcinfo/family_15.jpg","total":"156","lien":"https://www.dev.ayamesoft.com/plugnweb/word_app?call_func=change_family&id_family=15"},{"id":"17","name":"Téléphone portable","icone":"https://www.dev.ayamesoft.com/lib/upload/parcinfo/family_17.jpg","total":"0","lien":"https://www.dev.ayamesoft.com/plugnweb/word_app?call_func=change_family&id_family=17"},{"id":"18","name":"Totem","icone":"https://www.dev.ayamesoft.com/lib/upload/parcinfo/family_18.jpg","total":"0","lien":"https://www.dev.ayamesoft.com/plugnweb/word_app?call_func=change_family&id_family=18"}]}